[
  {
    "count": 1,
    "color": "Maroon",
    "title": "Swarm of Bats",
    "icon": "imp-laugh",
    "contents": [
      "subtitle | Medium swarm of tiny beasts, unaligned",
      "rule",
      "property | Armor class | 12",
      "property | Hit points | 22 (5d8)",
      "property | Speed | 0 ft., fly 30 ft.",
      "rule",
      "dndstats | 5 | 15 | 10 | 2 | 12 | 4",
      "rule",
      "property | Skills | ",
      "property | Damage Resistances | bludgeoning, piercing, slashing",
      "property | Condition Immunities | charmed, frightened, paralysed, petrified, prone, restrained, stunned",
      "property | Senses | blindsight 60 ft., passive Perception 11",
      "property | Languages | -",
      "property | Challenge | 1/4 (50)",
      "rule",
      "description | Echolocation | The swarm can 't use its blindsight while deafened.",
      "fill | 2",
      "description | Keen Hearing | The swarm has advantage on Wisdom (Perception) checks that rely on hearing.",
      "fill | 2",
      "description | Swarm | The swarm can occupy another creature's space and vice versa, and the swarm can move through any opening large enough for a Tiny bat. The swarm can't regain hit points or gain temporary hit points.",
      "fill | 2",
      "section | Actions",
      "description | Bites | Melee Weapon Attack: +4 to hit, reach 0 ft., one creature in the swarm 's space. Hit: 5 (2d4) piercing damage, or 2 (1d4) piercing damage if the swarm has half of its hit points or fewer."
    ],
    "tags": []
  }
]